airflow_report/__init__.py
airflow_report/__main__.py
astronomer_telescope/__init__.py
astronomer_telescope/__main__.py
astronomer_telescope/config.py
astronomer_telescope/getter_util.py
astronomer_telescope/util.py
astronomer_telescope/functions/__init__.py
astronomer_telescope/functions/astronomer_enterprise.py
astronomer_telescope/functions/autodiscover.py
astronomer_telescope/functions/cluster_info.py
astronomer_telescope/getters/__init__.py
astronomer_telescope/getters/docker.py
astronomer_telescope/getters/docker_client.py
astronomer_telescope/getters/kubernetes.py
astronomer_telescope/getters/kubernetes_client.py
astronomer_telescope/getters/local.py
astronomer_telescope/getters/ssh.py
astronomer_telescope-3.2.3.dist-info/LICENSE
astronomer_telescope-3.2.3.dist-info/METADATA
astronomer_telescope-3.2.3.dist-info/WHEEL
astronomer_telescope-3.2.3.dist-info/entry_points.txt
astronomer_telescope-3.2.3.dist-info/top_level.txt
astronomer_telescope-3.2.3.dist-info/RECORD
