Metadata-Version: 2.1
Name: astronomer-telescope
Version: 3.2.3
Summary: A tool to observe distant (or local!) Airflow installations, and gather metadata or other required data.
Author-email: Fritz Davenport <fritz@astronomer.io>, CETA Team <ceta@astronomer.io>, Astronomer <humans@astronomer.io>
License: All Rights Reserved
Project-URL: Homepage, https://astronomer.io
Project-URL: Source, https://github.com/astronomer/telescope/
Requires-Python: >=3.6.2
License-File: LICENSE
Requires-Dist: kubernetes >=21.7
Requires-Dist: fabric >=2.6.0
Requires-Dist: docker >=5.0.3
Requires-Dist: invoke >=1.6.0
Requires-Dist: PyYAML >=6.0
Requires-Dist: click >=8.0.3
Requires-Dist: lazyimport >=0.0.4
Requires-Dist: halo >=0.0.31
Requires-Dist: retrying >=1.3.3
Requires-Dist: rich >=11.1.0
Requires-Dist: importlib-metadata ; python_version < "3.8"
Provides-Extra: dev
Requires-Dist: pyinstaller >=4.10 ; extra == 'dev'
Requires-Dist: build ; extra == 'dev'
Requires-Dist: twine ; extra == 'dev'
Requires-Dist: pre-commit >=2.14 ; extra == 'dev'
Requires-Dist: ruff ; extra == 'dev'
Requires-Dist: black ; extra == 'dev'
Requires-Dist: pylint ; extra == 'dev'
Requires-Dist: isort ; extra == 'dev'
Requires-Dist: mkdocs ; extra == 'dev'
Requires-Dist: mkdocs-click ; extra == 'dev'
Requires-Dist: mkdocs-material ; extra == 'dev'
Requires-Dist: pygments ; extra == 'dev'
Requires-Dist: pytest ; extra == 'dev'
Requires-Dist: pytest-cov ; extra == 'dev'
Requires-Dist: pytest-sugar ; extra == 'dev'
Requires-Dist: pytest-mock ; extra == 'dev'
Requires-Dist: apache-airflow ; extra == 'dev'
